<?xml version="1.0" encoding="utf-8"?>
<!-- https://learn.microsoft.com/en-us/dotnet/fundamentals/package-validation/diagnostic-ids -->
<Suppressions xmlns:xsi="http://www.w3.org/2001/XMLSchema-instance" xmlns:xsd="http://www.w3.org/2001/XMLSchema">
  <Suppression>
    <DiagnosticId>CP0001</DiagnosticId>
    <Target>T:GuildWars2.Hero.Accounts.Gender</Target>
    <Left>lib/net462/GW2SDK.dll</Left>
    <Right>lib/net462/GW2SDK.dll</Right>
    <IsBaselineSuppression>true</IsBaselineSuppression>
  </Suppression>
  <Suppression>
    <DiagnosticId>CP0001</DiagnosticId>
    <Target>T:GuildWars2.Hero.Races.RaceName</Target>
    <Left>lib/net462/GW2SDK.dll</Left>
    <Right>lib/net462/GW2SDK.dll</Right>
    <IsBaselineSuppression>true</IsBaselineSuppression>
  </Suppression>
  <Suppression>
    <DiagnosticId>CP0001</DiagnosticId>
    <Target>T:GuildWars2.Items.ItemRestriction</Target>
    <Left>lib/net462/GW2SDK.dll</Left>
    <Right>lib/net462/GW2SDK.dll</Right>
    <IsBaselineSuppression>true</IsBaselineSuppression>
  </Suppression>
  <Suppression>
    <DiagnosticId>CP0001</DiagnosticId>
    <Target>T:GuildWars2.PageContext</Target>
    <Left>lib/net462/GW2SDK.dll</Left>
    <Right>lib/net462/GW2SDK.dll</Right>
    <IsBaselineSuppression>true</IsBaselineSuppression>
  </Suppression>
  <Suppression>
    <DiagnosticId>CP0001</DiagnosticId>
    <Target>T:GuildWars2.Hero.Accounts.Gender</Target>
    <Left>lib/net6.0/GW2SDK.dll</Left>
    <Right>lib/net6.0/GW2SDK.dll</Right>
    <IsBaselineSuppression>true</IsBaselineSuppression>
  </Suppression>
  <Suppression>
    <DiagnosticId>CP0001</DiagnosticId>
    <Target>T:GuildWars2.Hero.Races.RaceName</Target>
    <Left>lib/net6.0/GW2SDK.dll</Left>
    <Right>lib/net6.0/GW2SDK.dll</Right>
    <IsBaselineSuppression>true</IsBaselineSuppression>
  </Suppression>
  <Suppression>
    <DiagnosticId>CP0001</DiagnosticId>
    <Target>T:GuildWars2.Items.ItemRestriction</Target>
    <Left>lib/net6.0/GW2SDK.dll</Left>
    <Right>lib/net6.0/GW2SDK.dll</Right>
    <IsBaselineSuppression>true</IsBaselineSuppression>
  </Suppression>
  <Suppression>
    <DiagnosticId>CP0001</DiagnosticId>
    <Target>T:GuildWars2.PageContext</Target>
    <Left>lib/net6.0/GW2SDK.dll</Left>
    <Right>lib/net6.0/GW2SDK.dll</Right>
    <IsBaselineSuppression>true</IsBaselineSuppression>
  </Suppression>
  <Suppression>
    <DiagnosticId>CP0001</DiagnosticId>
    <Target>T:GuildWars2.Hero.Accounts.Gender</Target>
    <Left>lib/net8.0/GW2SDK.dll</Left>
    <Right>lib/net8.0/GW2SDK.dll</Right>
    <IsBaselineSuppression>true</IsBaselineSuppression>
  </Suppression>
  <Suppression>
    <DiagnosticId>CP0001</DiagnosticId>
    <Target>T:GuildWars2.Hero.Races.RaceName</Target>
    <Left>lib/net8.0/GW2SDK.dll</Left>
    <Right>lib/net8.0/GW2SDK.dll</Right>
    <IsBaselineSuppression>true</IsBaselineSuppression>
  </Suppression>
  <Suppression>
    <DiagnosticId>CP0001</DiagnosticId>
    <Target>T:GuildWars2.Items.ItemRestriction</Target>
    <Left>lib/net8.0/GW2SDK.dll</Left>
    <Right>lib/net8.0/GW2SDK.dll</Right>
    <IsBaselineSuppression>true</IsBaselineSuppression>
  </Suppression>
  <Suppression>
    <DiagnosticId>CP0001</DiagnosticId>
    <Target>T:GuildWars2.PageContext</Target>
    <Left>lib/net8.0/GW2SDK.dll</Left>
    <Right>lib/net8.0/GW2SDK.dll</Right>
    <IsBaselineSuppression>true</IsBaselineSuppression>
  </Suppression>
  <Suppression>
    <DiagnosticId>CP0001</DiagnosticId>
    <Target>T:GuildWars2.Hero.Accounts.Gender</Target>
    <Left>lib/netstandard2.0/GW2SDK.dll</Left>
    <Right>lib/netstandard2.0/GW2SDK.dll</Right>
    <IsBaselineSuppression>true</IsBaselineSuppression>
  </Suppression>
  <Suppression>
    <DiagnosticId>CP0001</DiagnosticId>
    <Target>T:GuildWars2.Hero.Races.RaceName</Target>
    <Left>lib/netstandard2.0/GW2SDK.dll</Left>
    <Right>lib/netstandard2.0/GW2SDK.dll</Right>
    <IsBaselineSuppression>true</IsBaselineSuppression>
  </Suppression>
  <Suppression>
    <DiagnosticId>CP0001</DiagnosticId>
    <Target>T:GuildWars2.Items.ItemRestriction</Target>
    <Left>lib/netstandard2.0/GW2SDK.dll</Left>
    <Right>lib/netstandard2.0/GW2SDK.dll</Right>
    <IsBaselineSuppression>true</IsBaselineSuppression>
  </Suppression>
  <Suppression>
    <DiagnosticId>CP0001</DiagnosticId>
    <Target>T:GuildWars2.PageContext</Target>
    <Left>lib/netstandard2.0/GW2SDK.dll</Left>
    <Right>lib/netstandard2.0/GW2SDK.dll</Right>
    <IsBaselineSuppression>true</IsBaselineSuppression>
  </Suppression>
  <Suppression>
    <DiagnosticId>CP0002</DiagnosticId>
    <Target>M:GuildWars2.Hero.Accounts.Character.get_Gender</Target>
    <Left>lib/net462/GW2SDK.dll</Left>
    <Right>lib/net462/GW2SDK.dll</Right>
    <IsBaselineSuppression>true</IsBaselineSuppression>
  </Suppression>
  <Suppression>
    <DiagnosticId>CP0002</DiagnosticId>
    <Target>M:GuildWars2.Hero.Accounts.Character.get_Race</Target>
    <Left>lib/net462/GW2SDK.dll</Left>
    <Right>lib/net462/GW2SDK.dll</Right>
    <IsBaselineSuppression>true</IsBaselineSuppression>
  </Suppression>
  <Suppression>
    <DiagnosticId>CP0002</DiagnosticId>
    <Target>M:GuildWars2.Hero.Accounts.Character.set_Gender(GuildWars2.Hero.Accounts.Gender)</Target>
    <Left>lib/net462/GW2SDK.dll</Left>
    <Right>lib/net462/GW2SDK.dll</Right>
    <IsBaselineSuppression>true</IsBaselineSuppression>
  </Suppression>
  <Suppression>
    <DiagnosticId>CP0002</DiagnosticId>
    <Target>M:GuildWars2.Hero.Accounts.CharacterSummary.get_Gender</Target>
    <Left>lib/net462/GW2SDK.dll</Left>
    <Right>lib/net462/GW2SDK.dll</Right>
    <IsBaselineSuppression>true</IsBaselineSuppression>
  </Suppression>
  <Suppression>
    <DiagnosticId>CP0002</DiagnosticId>
    <Target>M:GuildWars2.Hero.Accounts.CharacterSummary.get_Race</Target>
    <Left>lib/net462/GW2SDK.dll</Left>
    <Right>lib/net462/GW2SDK.dll</Right>
    <IsBaselineSuppression>true</IsBaselineSuppression>
  </Suppression>
  <Suppression>
    <DiagnosticId>CP0002</DiagnosticId>
    <Target>M:GuildWars2.Hero.Accounts.CharacterSummary.set_Gender(GuildWars2.Hero.Accounts.Gender)</Target>
    <Left>lib/net462/GW2SDK.dll</Left>
    <Right>lib/net462/GW2SDK.dll</Right>
    <IsBaselineSuppression>true</IsBaselineSuppression>
  </Suppression>
  <Suppression>
    <DiagnosticId>CP0002</DiagnosticId>
    <Target>M:GuildWars2.Hero.Equipment.Templates.EquipmentItem.get_UpgradeItemIds</Target>
    <Left>lib/net462/GW2SDK.dll</Left>
    <Right>lib/net462/GW2SDK.dll</Right>
    <IsBaselineSuppression>true</IsBaselineSuppression>
  </Suppression>
  <Suppression>
    <DiagnosticId>CP0002</DiagnosticId>
    <Target>M:GuildWars2.Hero.Equipment.Templates.EquipmentItem.set_UpgradeItemIds(System.Collections.Generic.IReadOnlyList{System.Int32})</Target>
    <Left>lib/net462/GW2SDK.dll</Left>
    <Right>lib/net462/GW2SDK.dll</Right>
    <IsBaselineSuppression>true</IsBaselineSuppression>
  </Suppression>
  <Suppression>
    <DiagnosticId>CP0002</DiagnosticId>
    <Target>M:GuildWars2.Hero.Equipment.Wardrobe.Skin.get_Restrictions</Target>
    <Left>lib/net462/GW2SDK.dll</Left>
    <Right>lib/net462/GW2SDK.dll</Right>
    <IsBaselineSuppression>true</IsBaselineSuppression>
  </Suppression>
  <Suppression>
    <DiagnosticId>CP0002</DiagnosticId>
    <Target>M:GuildWars2.Hero.Equipment.Wardrobe.Skin.set_Restrictions(System.Collections.Generic.IReadOnlyList{GuildWars2.Hero.Races.RaceName})</Target>
    <Left>lib/net462/GW2SDK.dll</Left>
    <Right>lib/net462/GW2SDK.dll</Right>
    <IsBaselineSuppression>true</IsBaselineSuppression>
  </Suppression>
  <Suppression>
    <DiagnosticId>CP0002</DiagnosticId>
    <Target>M:GuildWars2.Hero.Races.Race.get_Id</Target>
    <Left>lib/net462/GW2SDK.dll</Left>
    <Right>lib/net462/GW2SDK.dll</Right>
    <IsBaselineSuppression>true</IsBaselineSuppression>
  </Suppression>
  <Suppression>
    <DiagnosticId>CP0002</DiagnosticId>
    <Target>M:GuildWars2.Hero.Races.RacesClient.GetRaceByName(GuildWars2.Hero.Races.RaceName,GuildWars2.Language,GuildWars2.MissingMemberBehavior,System.Threading.CancellationToken)</Target>
    <Left>lib/net462/GW2SDK.dll</Left>
    <Right>lib/net462/GW2SDK.dll</Right>
    <IsBaselineSuppression>true</IsBaselineSuppression>
  </Suppression>
  <Suppression>
    <DiagnosticId>CP0002</DiagnosticId>
    <Target>M:GuildWars2.Hero.Races.RacesClient.GetRacesByNames(System.Collections.Generic.IReadOnlyCollection{GuildWars2.Hero.Races.RaceName},GuildWars2.Language,GuildWars2.MissingMemberBehavior,System.Threading.CancellationToken)</Target>
    <Left>lib/net462/GW2SDK.dll</Left>
    <Right>lib/net462/GW2SDK.dll</Right>
    <IsBaselineSuppression>true</IsBaselineSuppression>
  </Suppression>
  <Suppression>
    <DiagnosticId>CP0002</DiagnosticId>
    <Target>M:GuildWars2.Hero.StoryJournal.BackgroundStories.BackgroundStoryAnswer.get_Races</Target>
    <Left>lib/net462/GW2SDK.dll</Left>
    <Right>lib/net462/GW2SDK.dll</Right>
    <IsBaselineSuppression>true</IsBaselineSuppression>
  </Suppression>
  <Suppression>
    <DiagnosticId>CP0002</DiagnosticId>
    <Target>M:GuildWars2.Hero.StoryJournal.BackgroundStories.BackgroundStoryQuestion.get_Races</Target>
    <Left>lib/net462/GW2SDK.dll</Left>
    <Right>lib/net462/GW2SDK.dll</Right>
    <IsBaselineSuppression>true</IsBaselineSuppression>
  </Suppression>
  <Suppression>
    <DiagnosticId>CP0002</DiagnosticId>
    <Target>M:GuildWars2.Hero.StoryJournal.Stories.Story.get_Races</Target>
    <Left>lib/net462/GW2SDK.dll</Left>
    <Right>lib/net462/GW2SDK.dll</Right>
    <IsBaselineSuppression>true</IsBaselineSuppression>
  </Suppression>
  <Suppression>
    <DiagnosticId>CP0002</DiagnosticId>
    <Target>M:GuildWars2.Items.Item.get_Restrictions</Target>
    <Left>lib/net462/GW2SDK.dll</Left>
    <Right>lib/net462/GW2SDK.dll</Right>
    <IsBaselineSuppression>true</IsBaselineSuppression>
  </Suppression>
  <Suppression>
    <DiagnosticId>CP0002</DiagnosticId>
    <Target>M:GuildWars2.Items.Item.set_Restrictions(System.Collections.Generic.IReadOnlyCollection{GuildWars2.Items.ItemRestriction})</Target>
    <Left>lib/net462/GW2SDK.dll</Left>
    <Right>lib/net462/GW2SDK.dll</Right>
    <IsBaselineSuppression>true</IsBaselineSuppression>
  </Suppression>
  <Suppression>
    <DiagnosticId>CP0002</DiagnosticId>
    <Target>M:GuildWars2.Items.ItemsClient.GetItemStatsIndex(System.Threading.CancellationToken)</Target>
    <Left>lib/net462/GW2SDK.dll</Left>
    <Right>lib/net462/GW2SDK.dll</Right>
    <IsBaselineSuppression>true</IsBaselineSuppression>
  </Suppression>
  <Suppression>
    <DiagnosticId>CP0002</DiagnosticId>
    <Target>M:GuildWars2.MessageContext.get_PageContext</Target>
    <Left>lib/net462/GW2SDK.dll</Left>
    <Right>lib/net462/GW2SDK.dll</Right>
    <IsBaselineSuppression>true</IsBaselineSuppression>
  </Suppression>
  <Suppression>
    <DiagnosticId>CP0002</DiagnosticId>
    <Target>M:GuildWars2.MessageContext.get_ResultContext</Target>
    <Left>lib/net462/GW2SDK.dll</Left>
    <Right>lib/net462/GW2SDK.dll</Right>
    <IsBaselineSuppression>true</IsBaselineSuppression>
  </Suppression>
  <Suppression>
    <DiagnosticId>CP0002</DiagnosticId>
    <Target>M:GuildWars2.Mumble.Identity.get_Race</Target>
    <Left>lib/net462/GW2SDK.dll</Left>
    <Right>lib/net462/GW2SDK.dll</Right>
    <IsBaselineSuppression>true</IsBaselineSuppression>
  </Suppression>
  <Suppression>
    <DiagnosticId>CP0002</DiagnosticId>
    <Target>M:GuildWars2.Hero.Accounts.Character.get_Gender</Target>
    <Left>lib/net6.0/GW2SDK.dll</Left>
    <Right>lib/net6.0/GW2SDK.dll</Right>
    <IsBaselineSuppression>true</IsBaselineSuppression>
  </Suppression>
  <Suppression>
    <DiagnosticId>CP0002</DiagnosticId>
    <Target>M:GuildWars2.Hero.Accounts.Character.get_Race</Target>
    <Left>lib/net6.0/GW2SDK.dll</Left>
    <Right>lib/net6.0/GW2SDK.dll</Right>
    <IsBaselineSuppression>true</IsBaselineSuppression>
  </Suppression>
  <Suppression>
    <DiagnosticId>CP0002</DiagnosticId>
    <Target>M:GuildWars2.Hero.Accounts.Character.set_Gender(GuildWars2.Hero.Accounts.Gender)</Target>
    <Left>lib/net6.0/GW2SDK.dll</Left>
    <Right>lib/net6.0/GW2SDK.dll</Right>
    <IsBaselineSuppression>true</IsBaselineSuppression>
  </Suppression>
  <Suppression>
    <DiagnosticId>CP0002</DiagnosticId>
    <Target>M:GuildWars2.Hero.Accounts.CharacterSummary.get_Gender</Target>
    <Left>lib/net6.0/GW2SDK.dll</Left>
    <Right>lib/net6.0/GW2SDK.dll</Right>
    <IsBaselineSuppression>true</IsBaselineSuppression>
  </Suppression>
  <Suppression>
    <DiagnosticId>CP0002</DiagnosticId>
    <Target>M:GuildWars2.Hero.Accounts.CharacterSummary.get_Race</Target>
    <Left>lib/net6.0/GW2SDK.dll</Left>
    <Right>lib/net6.0/GW2SDK.dll</Right>
    <IsBaselineSuppression>true</IsBaselineSuppression>
  </Suppression>
  <Suppression>
    <DiagnosticId>CP0002</DiagnosticId>
    <Target>M:GuildWars2.Hero.Accounts.CharacterSummary.set_Gender(GuildWars2.Hero.Accounts.Gender)</Target>
    <Left>lib/net6.0/GW2SDK.dll</Left>
    <Right>lib/net6.0/GW2SDK.dll</Right>
    <IsBaselineSuppression>true</IsBaselineSuppression>
  </Suppression>
  <Suppression>
    <DiagnosticId>CP0002</DiagnosticId>
    <Target>M:GuildWars2.Hero.Equipment.Templates.EquipmentItem.get_UpgradeItemIds</Target>
    <Left>lib/net6.0/GW2SDK.dll</Left>
    <Right>lib/net6.0/GW2SDK.dll</Right>
    <IsBaselineSuppression>true</IsBaselineSuppression>
  </Suppression>
  <Suppression>
    <DiagnosticId>CP0002</DiagnosticId>
    <Target>M:GuildWars2.Hero.Equipment.Templates.EquipmentItem.set_UpgradeItemIds(System.Collections.Generic.IReadOnlyList{System.Int32})</Target>
    <Left>lib/net6.0/GW2SDK.dll</Left>
    <Right>lib/net6.0/GW2SDK.dll</Right>
    <IsBaselineSuppression>true</IsBaselineSuppression>
  </Suppression>
  <Suppression>
    <DiagnosticId>CP0002</DiagnosticId>
    <Target>M:GuildWars2.Hero.Equipment.Wardrobe.Skin.get_Restrictions</Target>
    <Left>lib/net6.0/GW2SDK.dll</Left>
    <Right>lib/net6.0/GW2SDK.dll</Right>
    <IsBaselineSuppression>true</IsBaselineSuppression>
  </Suppression>
  <Suppression>
    <DiagnosticId>CP0002</DiagnosticId>
    <Target>M:GuildWars2.Hero.Equipment.Wardrobe.Skin.set_Restrictions(System.Collections.Generic.IReadOnlyList{GuildWars2.Hero.Races.RaceName})</Target>
    <Left>lib/net6.0/GW2SDK.dll</Left>
    <Right>lib/net6.0/GW2SDK.dll</Right>
    <IsBaselineSuppression>true</IsBaselineSuppression>
  </Suppression>
  <Suppression>
    <DiagnosticId>CP0002</DiagnosticId>
    <Target>M:GuildWars2.Hero.Races.Race.get_Id</Target>
    <Left>lib/net6.0/GW2SDK.dll</Left>
    <Right>lib/net6.0/GW2SDK.dll</Right>
    <IsBaselineSuppression>true</IsBaselineSuppression>
  </Suppression>
  <Suppression>
    <DiagnosticId>CP0002</DiagnosticId>
    <Target>M:GuildWars2.Hero.Races.RacesClient.GetRaceByName(GuildWars2.Hero.Races.RaceName,GuildWars2.Language,GuildWars2.MissingMemberBehavior,System.Threading.CancellationToken)</Target>
    <Left>lib/net6.0/GW2SDK.dll</Left>
    <Right>lib/net6.0/GW2SDK.dll</Right>
    <IsBaselineSuppression>true</IsBaselineSuppression>
  </Suppression>
  <Suppression>
    <DiagnosticId>CP0002</DiagnosticId>
    <Target>M:GuildWars2.Hero.Races.RacesClient.GetRacesByNames(System.Collections.Generic.IReadOnlyCollection{GuildWars2.Hero.Races.RaceName},GuildWars2.Language,GuildWars2.MissingMemberBehavior,System.Threading.CancellationToken)</Target>
    <Left>lib/net6.0/GW2SDK.dll</Left>
    <Right>lib/net6.0/GW2SDK.dll</Right>
    <IsBaselineSuppression>true</IsBaselineSuppression>
  </Suppression>
  <Suppression>
    <DiagnosticId>CP0002</DiagnosticId>
    <Target>M:GuildWars2.Hero.StoryJournal.BackgroundStories.BackgroundStoryAnswer.get_Races</Target>
    <Left>lib/net6.0/GW2SDK.dll</Left>
    <Right>lib/net6.0/GW2SDK.dll</Right>
    <IsBaselineSuppression>true</IsBaselineSuppression>
  </Suppression>
  <Suppression>
    <DiagnosticId>CP0002</DiagnosticId>
    <Target>M:GuildWars2.Hero.StoryJournal.BackgroundStories.BackgroundStoryQuestion.get_Races</Target>
    <Left>lib/net6.0/GW2SDK.dll</Left>
    <Right>lib/net6.0/GW2SDK.dll</Right>
    <IsBaselineSuppression>true</IsBaselineSuppression>
  </Suppression>
  <Suppression>
    <DiagnosticId>CP0002</DiagnosticId>
    <Target>M:GuildWars2.Hero.StoryJournal.Stories.Story.get_Races</Target>
    <Left>lib/net6.0/GW2SDK.dll</Left>
    <Right>lib/net6.0/GW2SDK.dll</Right>
    <IsBaselineSuppression>true</IsBaselineSuppression>
  </Suppression>
  <Suppression>
    <DiagnosticId>CP0002</DiagnosticId>
    <Target>M:GuildWars2.Items.Item.get_Restrictions</Target>
    <Left>lib/net6.0/GW2SDK.dll</Left>
    <Right>lib/net6.0/GW2SDK.dll</Right>
    <IsBaselineSuppression>true</IsBaselineSuppression>
  </Suppression>
  <Suppression>
    <DiagnosticId>CP0002</DiagnosticId>
    <Target>M:GuildWars2.Items.Item.set_Restrictions(System.Collections.Generic.IReadOnlyCollection{GuildWars2.Items.ItemRestriction})</Target>
    <Left>lib/net6.0/GW2SDK.dll</Left>
    <Right>lib/net6.0/GW2SDK.dll</Right>
    <IsBaselineSuppression>true</IsBaselineSuppression>
  </Suppression>
  <Suppression>
    <DiagnosticId>CP0002</DiagnosticId>
    <Target>M:GuildWars2.Items.ItemsClient.GetItemStatsIndex(System.Threading.CancellationToken)</Target>
    <Left>lib/net6.0/GW2SDK.dll</Left>
    <Right>lib/net6.0/GW2SDK.dll</Right>
    <IsBaselineSuppression>true</IsBaselineSuppression>
  </Suppression>
  <Suppression>
    <DiagnosticId>CP0002</DiagnosticId>
    <Target>M:GuildWars2.MessageContext.get_PageContext</Target>
    <Left>lib/net6.0/GW2SDK.dll</Left>
    <Right>lib/net6.0/GW2SDK.dll</Right>
    <IsBaselineSuppression>true</IsBaselineSuppression>
  </Suppression>
  <Suppression>
    <DiagnosticId>CP0002</DiagnosticId>
    <Target>M:GuildWars2.MessageContext.get_ResultContext</Target>
    <Left>lib/net6.0/GW2SDK.dll</Left>
    <Right>lib/net6.0/GW2SDK.dll</Right>
    <IsBaselineSuppression>true</IsBaselineSuppression>
  </Suppression>
  <Suppression>
    <DiagnosticId>CP0002</DiagnosticId>
    <Target>M:GuildWars2.Mumble.Identity.get_Race</Target>
    <Left>lib/net6.0/GW2SDK.dll</Left>
    <Right>lib/net6.0/GW2SDK.dll</Right>
    <IsBaselineSuppression>true</IsBaselineSuppression>
  </Suppression>
  <Suppression>
    <DiagnosticId>CP0002</DiagnosticId>
    <Target>M:GuildWars2.Hero.Accounts.Character.get_Gender</Target>
    <Left>lib/net8.0/GW2SDK.dll</Left>
    <Right>lib/net8.0/GW2SDK.dll</Right>
    <IsBaselineSuppression>true</IsBaselineSuppression>
  </Suppression>
  <Suppression>
    <DiagnosticId>CP0002</DiagnosticId>
    <Target>M:GuildWars2.Hero.Accounts.Character.get_Race</Target>
    <Left>lib/net8.0/GW2SDK.dll</Left>
    <Right>lib/net8.0/GW2SDK.dll</Right>
    <IsBaselineSuppression>true</IsBaselineSuppression>
  </Suppression>
  <Suppression>
    <DiagnosticId>CP0002</DiagnosticId>
    <Target>M:GuildWars2.Hero.Accounts.Character.set_Gender(GuildWars2.Hero.Accounts.Gender)</Target>
    <Left>lib/net8.0/GW2SDK.dll</Left>
    <Right>lib/net8.0/GW2SDK.dll</Right>
    <IsBaselineSuppression>true</IsBaselineSuppression>
  </Suppression>
  <Suppression>
    <DiagnosticId>CP0002</DiagnosticId>
    <Target>M:GuildWars2.Hero.Accounts.CharacterSummary.get_Gender</Target>
    <Left>lib/net8.0/GW2SDK.dll</Left>
    <Right>lib/net8.0/GW2SDK.dll</Right>
    <IsBaselineSuppression>true</IsBaselineSuppression>
  </Suppression>
  <Suppression>
    <DiagnosticId>CP0002</DiagnosticId>
    <Target>M:GuildWars2.Hero.Accounts.CharacterSummary.get_Race</Target>
    <Left>lib/net8.0/GW2SDK.dll</Left>
    <Right>lib/net8.0/GW2SDK.dll</Right>
    <IsBaselineSuppression>true</IsBaselineSuppression>
  </Suppression>
  <Suppression>
    <DiagnosticId>CP0002</DiagnosticId>
    <Target>M:GuildWars2.Hero.Accounts.CharacterSummary.set_Gender(GuildWars2.Hero.Accounts.Gender)</Target>
    <Left>lib/net8.0/GW2SDK.dll</Left>
    <Right>lib/net8.0/GW2SDK.dll</Right>
    <IsBaselineSuppression>true</IsBaselineSuppression>
  </Suppression>
  <Suppression>
    <DiagnosticId>CP0002</DiagnosticId>
    <Target>M:GuildWars2.Hero.Equipment.Templates.EquipmentItem.get_UpgradeItemIds</Target>
    <Left>lib/net8.0/GW2SDK.dll</Left>
    <Right>lib/net8.0/GW2SDK.dll</Right>
    <IsBaselineSuppression>true</IsBaselineSuppression>
  </Suppression>
  <Suppression>
    <DiagnosticId>CP0002</DiagnosticId>
    <Target>M:GuildWars2.Hero.Equipment.Templates.EquipmentItem.set_UpgradeItemIds(System.Collections.Generic.IReadOnlyList{System.Int32})</Target>
    <Left>lib/net8.0/GW2SDK.dll</Left>
    <Right>lib/net8.0/GW2SDK.dll</Right>
    <IsBaselineSuppression>true</IsBaselineSuppression>
  </Suppression>
  <Suppression>
    <DiagnosticId>CP0002</DiagnosticId>
    <Target>M:GuildWars2.Hero.Equipment.Wardrobe.Skin.get_Restrictions</Target>
    <Left>lib/net8.0/GW2SDK.dll</Left>
    <Right>lib/net8.0/GW2SDK.dll</Right>
    <IsBaselineSuppression>true</IsBaselineSuppression>
  </Suppression>
  <Suppression>
    <DiagnosticId>CP0002</DiagnosticId>
    <Target>M:GuildWars2.Hero.Equipment.Wardrobe.Skin.set_Restrictions(System.Collections.Generic.IReadOnlyList{GuildWars2.Hero.Races.RaceName})</Target>
    <Left>lib/net8.0/GW2SDK.dll</Left>
    <Right>lib/net8.0/GW2SDK.dll</Right>
    <IsBaselineSuppression>true</IsBaselineSuppression>
  </Suppression>
  <Suppression>
    <DiagnosticId>CP0002</DiagnosticId>
    <Target>M:GuildWars2.Hero.Races.Race.get_Id</Target>
    <Left>lib/net8.0/GW2SDK.dll</Left>
    <Right>lib/net8.0/GW2SDK.dll</Right>
    <IsBaselineSuppression>true</IsBaselineSuppression>
  </Suppression>
  <Suppression>
    <DiagnosticId>CP0002</DiagnosticId>
    <Target>M:GuildWars2.Hero.Races.RacesClient.GetRaceByName(GuildWars2.Hero.Races.RaceName,GuildWars2.Language,GuildWars2.MissingMemberBehavior,System.Threading.CancellationToken)</Target>
    <Left>lib/net8.0/GW2SDK.dll</Left>
    <Right>lib/net8.0/GW2SDK.dll</Right>
    <IsBaselineSuppression>true</IsBaselineSuppression>
  </Suppression>
  <Suppression>
    <DiagnosticId>CP0002</DiagnosticId>
    <Target>M:GuildWars2.Hero.Races.RacesClient.GetRacesByNames(System.Collections.Generic.IReadOnlyCollection{GuildWars2.Hero.Races.RaceName},GuildWars2.Language,GuildWars2.MissingMemberBehavior,System.Threading.CancellationToken)</Target>
    <Left>lib/net8.0/GW2SDK.dll</Left>
    <Right>lib/net8.0/GW2SDK.dll</Right>
    <IsBaselineSuppression>true</IsBaselineSuppression>
  </Suppression>
  <Suppression>
    <DiagnosticId>CP0002</DiagnosticId>
    <Target>M:GuildWars2.Hero.StoryJournal.BackgroundStories.BackgroundStoryAnswer.get_Races</Target>
    <Left>lib/net8.0/GW2SDK.dll</Left>
    <Right>lib/net8.0/GW2SDK.dll</Right>
    <IsBaselineSuppression>true</IsBaselineSuppression>
  </Suppression>
  <Suppression>
    <DiagnosticId>CP0002</DiagnosticId>
    <Target>M:GuildWars2.Hero.StoryJournal.BackgroundStories.BackgroundStoryQuestion.get_Races</Target>
    <Left>lib/net8.0/GW2SDK.dll</Left>
    <Right>lib/net8.0/GW2SDK.dll</Right>
    <IsBaselineSuppression>true</IsBaselineSuppression>
  </Suppression>
  <Suppression>
    <DiagnosticId>CP0002</DiagnosticId>
    <Target>M:GuildWars2.Hero.StoryJournal.Stories.Story.get_Races</Target>
    <Left>lib/net8.0/GW2SDK.dll</Left>
    <Right>lib/net8.0/GW2SDK.dll</Right>
    <IsBaselineSuppression>true</IsBaselineSuppression>
  </Suppression>
  <Suppression>
    <DiagnosticId>CP0002</DiagnosticId>
    <Target>M:GuildWars2.Items.Item.get_Restrictions</Target>
    <Left>lib/net8.0/GW2SDK.dll</Left>
    <Right>lib/net8.0/GW2SDK.dll</Right>
    <IsBaselineSuppression>true</IsBaselineSuppression>
  </Suppression>
  <Suppression>
    <DiagnosticId>CP0002</DiagnosticId>
    <Target>M:GuildWars2.Items.Item.set_Restrictions(System.Collections.Generic.IReadOnlyCollection{GuildWars2.Items.ItemRestriction})</Target>
    <Left>lib/net8.0/GW2SDK.dll</Left>
    <Right>lib/net8.0/GW2SDK.dll</Right>
    <IsBaselineSuppression>true</IsBaselineSuppression>
  </Suppression>
  <Suppression>
    <DiagnosticId>CP0002</DiagnosticId>
    <Target>M:GuildWars2.Items.ItemsClient.GetItemStatsIndex(System.Threading.CancellationToken)</Target>
    <Left>lib/net8.0/GW2SDK.dll</Left>
    <Right>lib/net8.0/GW2SDK.dll</Right>
    <IsBaselineSuppression>true</IsBaselineSuppression>
  </Suppression>
  <Suppression>
    <DiagnosticId>CP0002</DiagnosticId>
    <Target>M:GuildWars2.MessageContext.get_PageContext</Target>
    <Left>lib/net8.0/GW2SDK.dll</Left>
    <Right>lib/net8.0/GW2SDK.dll</Right>
    <IsBaselineSuppression>true</IsBaselineSuppression>
  </Suppression>
  <Suppression>
    <DiagnosticId>CP0002</DiagnosticId>
    <Target>M:GuildWars2.MessageContext.get_ResultContext</Target>
    <Left>lib/net8.0/GW2SDK.dll</Left>
    <Right>lib/net8.0/GW2SDK.dll</Right>
    <IsBaselineSuppression>true</IsBaselineSuppression>
  </Suppression>
  <Suppression>
    <DiagnosticId>CP0002</DiagnosticId>
    <Target>M:GuildWars2.Mumble.Identity.get_Race</Target>
    <Left>lib/net8.0/GW2SDK.dll</Left>
    <Right>lib/net8.0/GW2SDK.dll</Right>
    <IsBaselineSuppression>true</IsBaselineSuppression>
  </Suppression>
  <Suppression>
    <DiagnosticId>CP0002</DiagnosticId>
    <Target>M:GuildWars2.Hero.Accounts.Character.get_Gender</Target>
    <Left>lib/netstandard2.0/GW2SDK.dll</Left>
    <Right>lib/netstandard2.0/GW2SDK.dll</Right>
    <IsBaselineSuppression>true</IsBaselineSuppression>
  </Suppression>
  <Suppression>
    <DiagnosticId>CP0002</DiagnosticId>
    <Target>M:GuildWars2.Hero.Accounts.Character.get_Race</Target>
    <Left>lib/netstandard2.0/GW2SDK.dll</Left>
    <Right>lib/netstandard2.0/GW2SDK.dll</Right>
    <IsBaselineSuppression>true</IsBaselineSuppression>
  </Suppression>
  <Suppression>
    <DiagnosticId>CP0002</DiagnosticId>
    <Target>M:GuildWars2.Hero.Accounts.Character.set_Gender(GuildWars2.Hero.Accounts.Gender)</Target>
    <Left>lib/netstandard2.0/GW2SDK.dll</Left>
    <Right>lib/netstandard2.0/GW2SDK.dll</Right>
    <IsBaselineSuppression>true</IsBaselineSuppression>
  </Suppression>
  <Suppression>
    <DiagnosticId>CP0002</DiagnosticId>
    <Target>M:GuildWars2.Hero.Accounts.CharacterSummary.get_Gender</Target>
    <Left>lib/netstandard2.0/GW2SDK.dll</Left>
    <Right>lib/netstandard2.0/GW2SDK.dll</Right>
    <IsBaselineSuppression>true</IsBaselineSuppression>
  </Suppression>
  <Suppression>
    <DiagnosticId>CP0002</DiagnosticId>
    <Target>M:GuildWars2.Hero.Accounts.CharacterSummary.get_Race</Target>
    <Left>lib/netstandard2.0/GW2SDK.dll</Left>
    <Right>lib/netstandard2.0/GW2SDK.dll</Right>
    <IsBaselineSuppression>true</IsBaselineSuppression>
  </Suppression>
  <Suppression>
    <DiagnosticId>CP0002</DiagnosticId>
    <Target>M:GuildWars2.Hero.Accounts.CharacterSummary.set_Gender(GuildWars2.Hero.Accounts.Gender)</Target>
    <Left>lib/netstandard2.0/GW2SDK.dll</Left>
    <Right>lib/netstandard2.0/GW2SDK.dll</Right>
    <IsBaselineSuppression>true</IsBaselineSuppression>
  </Suppression>
  <Suppression>
    <DiagnosticId>CP0002</DiagnosticId>
    <Target>M:GuildWars2.Hero.Equipment.Templates.EquipmentItem.get_UpgradeItemIds</Target>
    <Left>lib/netstandard2.0/GW2SDK.dll</Left>
    <Right>lib/netstandard2.0/GW2SDK.dll</Right>
    <IsBaselineSuppression>true</IsBaselineSuppression>
  </Suppression>
  <Suppression>
    <DiagnosticId>CP0002</DiagnosticId>
    <Target>M:GuildWars2.Hero.Equipment.Templates.EquipmentItem.set_UpgradeItemIds(System.Collections.Generic.IReadOnlyList{System.Int32})</Target>
    <Left>lib/netstandard2.0/GW2SDK.dll</Left>
    <Right>lib/netstandard2.0/GW2SDK.dll</Right>
    <IsBaselineSuppression>true</IsBaselineSuppression>
  </Suppression>
  <Suppression>
    <DiagnosticId>CP0002</DiagnosticId>
    <Target>M:GuildWars2.Hero.Equipment.Wardrobe.Skin.get_Restrictions</Target>
    <Left>lib/netstandard2.0/GW2SDK.dll</Left>
    <Right>lib/netstandard2.0/GW2SDK.dll</Right>
    <IsBaselineSuppression>true</IsBaselineSuppression>
  </Suppression>
  <Suppression>
    <DiagnosticId>CP0002</DiagnosticId>
    <Target>M:GuildWars2.Hero.Equipment.Wardrobe.Skin.set_Restrictions(System.Collections.Generic.IReadOnlyList{GuildWars2.Hero.Races.RaceName})</Target>
    <Left>lib/netstandard2.0/GW2SDK.dll</Left>
    <Right>lib/netstandard2.0/GW2SDK.dll</Right>
    <IsBaselineSuppression>true</IsBaselineSuppression>
  </Suppression>
  <Suppression>
    <DiagnosticId>CP0002</DiagnosticId>
    <Target>M:GuildWars2.Hero.Races.Race.get_Id</Target>
    <Left>lib/netstandard2.0/GW2SDK.dll</Left>
    <Right>lib/netstandard2.0/GW2SDK.dll</Right>
    <IsBaselineSuppression>true</IsBaselineSuppression>
  </Suppression>
  <Suppression>
    <DiagnosticId>CP0002</DiagnosticId>
    <Target>M:GuildWars2.Hero.Races.RacesClient.GetRaceByName(GuildWars2.Hero.Races.RaceName,GuildWars2.Language,GuildWars2.MissingMemberBehavior,System.Threading.CancellationToken)</Target>
    <Left>lib/netstandard2.0/GW2SDK.dll</Left>
    <Right>lib/netstandard2.0/GW2SDK.dll</Right>
    <IsBaselineSuppression>true</IsBaselineSuppression>
  </Suppression>
  <Suppression>
    <DiagnosticId>CP0002</DiagnosticId>
    <Target>M:GuildWars2.Hero.Races.RacesClient.GetRacesByNames(System.Collections.Generic.IReadOnlyCollection{GuildWars2.Hero.Races.RaceName},GuildWars2.Language,GuildWars2.MissingMemberBehavior,System.Threading.CancellationToken)</Target>
    <Left>lib/netstandard2.0/GW2SDK.dll</Left>
    <Right>lib/netstandard2.0/GW2SDK.dll</Right>
    <IsBaselineSuppression>true</IsBaselineSuppression>
  </Suppression>
  <Suppression>
    <DiagnosticId>CP0002</DiagnosticId>
    <Target>M:GuildWars2.Hero.StoryJournal.BackgroundStories.BackgroundStoryAnswer.get_Races</Target>
    <Left>lib/netstandard2.0/GW2SDK.dll</Left>
    <Right>lib/netstandard2.0/GW2SDK.dll</Right>
    <IsBaselineSuppression>true</IsBaselineSuppression>
  </Suppression>
  <Suppression>
    <DiagnosticId>CP0002</DiagnosticId>
    <Target>M:GuildWars2.Hero.StoryJournal.BackgroundStories.BackgroundStoryQuestion.get_Races</Target>
    <Left>lib/netstandard2.0/GW2SDK.dll</Left>
    <Right>lib/netstandard2.0/GW2SDK.dll</Right>
    <IsBaselineSuppression>true</IsBaselineSuppression>
  </Suppression>
  <Suppression>
    <DiagnosticId>CP0002</DiagnosticId>
    <Target>M:GuildWars2.Hero.StoryJournal.Stories.Story.get_Races</Target>
    <Left>lib/netstandard2.0/GW2SDK.dll</Left>
    <Right>lib/netstandard2.0/GW2SDK.dll</Right>
    <IsBaselineSuppression>true</IsBaselineSuppression>
  </Suppression>
  <Suppression>
    <DiagnosticId>CP0002</DiagnosticId>
    <Target>M:GuildWars2.Items.Item.get_Restrictions</Target>
    <Left>lib/netstandard2.0/GW2SDK.dll</Left>
    <Right>lib/netstandard2.0/GW2SDK.dll</Right>
    <IsBaselineSuppression>true</IsBaselineSuppression>
  </Suppression>
  <Suppression>
    <DiagnosticId>CP0002</DiagnosticId>
    <Target>M:GuildWars2.Items.Item.set_Restrictions(System.Collections.Generic.IReadOnlyCollection{GuildWars2.Items.ItemRestriction})</Target>
    <Left>lib/netstandard2.0/GW2SDK.dll</Left>
    <Right>lib/netstandard2.0/GW2SDK.dll</Right>
    <IsBaselineSuppression>true</IsBaselineSuppression>
  </Suppression>
  <Suppression>
    <DiagnosticId>CP0002</DiagnosticId>
    <Target>M:GuildWars2.Items.ItemsClient.GetItemStatsIndex(System.Threading.CancellationToken)</Target>
    <Left>lib/netstandard2.0/GW2SDK.dll</Left>
    <Right>lib/netstandard2.0/GW2SDK.dll</Right>
    <IsBaselineSuppression>true</IsBaselineSuppression>
  </Suppression>
  <Suppression>
    <DiagnosticId>CP0002</DiagnosticId>
    <Target>M:GuildWars2.MessageContext.get_PageContext</Target>
    <Left>lib/netstandard2.0/GW2SDK.dll</Left>
    <Right>lib/netstandard2.0/GW2SDK.dll</Right>
    <IsBaselineSuppression>true</IsBaselineSuppression>
  </Suppression>
  <Suppression>
    <DiagnosticId>CP0002</DiagnosticId>
    <Target>M:GuildWars2.MessageContext.get_ResultContext</Target>
    <Left>lib/netstandard2.0/GW2SDK.dll</Left>
    <Right>lib/netstandard2.0/GW2SDK.dll</Right>
    <IsBaselineSuppression>true</IsBaselineSuppression>
  </Suppression>
  <Suppression>
    <DiagnosticId>CP0002</DiagnosticId>
    <Target>M:GuildWars2.Mumble.Identity.get_Race</Target>
    <Left>lib/netstandard2.0/GW2SDK.dll</Left>
    <Right>lib/netstandard2.0/GW2SDK.dll</Right>
    <IsBaselineSuppression>true</IsBaselineSuppression>
  </Suppression>
</Suppressions>